shmtorch/__init__.py
shmtorch/shared_memory.py
shmtorch/shmtorch.py
shmtorch-0.4.0.dist-info/WHEEL
shmtorch-0.4.0.dist-info/METADATA
shmtorch-0.4.0.dist-info/RECORD
