Metadata-Version: 2.1
Name: shmtorch
Version: 0.4.0
Summary: shmtorch is an extension for PyTorch, which allows sharing DNN model weight tensors via Shared Memory.
Author: freckie
Author-email: freckie@frec.kr
Requires-Python: >=3.10,<4.0
Classifier: Programming Language :: Python :: 3
Classifier: Programming Language :: Python :: 3.10
Requires-Dist: numpy (>=1.22.4,<2.0.0)
Requires-Dist: requests (>=2.28,<3.0)
Requires-Dist: torch (>=1.11.0,<2.0.0)
